pcjs_api.py
pcjs_api-1.0.dist-info/LICENSE
pcjs_api-1.0.dist-info/METADATA
pcjs_api-1.0.dist-info/WHEEL
pcjs_api-1.0.dist-info/top_level.txt
pcjs_api-1.0.dist-info/RECORD
